{
  "project_info": {
    "project_number": "1013526163721",
    "project_id": "new-world-011",
    "storage_bucket": "new-world-011.appspot.com"
  },
  "client": [
    {
      "client_info": {
        "mobilesdk_app_id": "1:1013526163721:android:11794788acd4f50a04a3d8",
        "android_client_info": {
          "package_name": "com.newworld.onelist"
        }
      },
      "oauth_client": [
        {
          "client_id": "1013526163721-m5mfl314ke5otvdn12c76ddm7umok6ks.apps.googleusercontent.com",
          "client_type": 3
        }
      ],
      "api_key": [
        {
          "current_key": "AIzaSyBM1bDzoJ4lxZgRGaTxRi8MQaPGmLQKOg0"
        }
      ],
      "services": {
        "appinvite_service": {
          "other_platform_oauth_client": [
            {
              "client_id": "1013526163721-m5mfl314ke5otvdn12c76ddm7umok6ks.apps.googleusercontent.com",
              "client_type": 3
            }
          ]
        }
      }
    }
  ],
  "configuration_version": "1"
}